[
  {
    "inputs": [],
    "stateMutability": "nonpayable",
    "type": "constructor"
  },
  {
    "inputs": [],
    "name": "ECDSAInvalidSignature",
    "type": "error"
  },
  {
    "inputs": [
      {
        "internalType": "uint256",
        "name": "length",
        "type": "uint256"
      }
    ],
    "name": "ECDSAInvalidSignatureLength",
    "type": "error"
  },
  {
    "inputs": [
      {
        "internalType": "bytes32",
        "name": "s",
        "type": "bytes32"
      }
    ],
    "name": "ECDSAInvalidSignatureS",
    "type": "error"
  },
  {
    "inputs": [],
    "name": "InvalidShortString",
    "type": "error"
  },
  {
    "inputs": [],
    "name": "SignerNotMessageSender",
    "type": "error"
  },
  {
    "inputs": [],
    "name": "SignerNotOwner",
    "type": "error"
  },
  {
    "inputs": [
      {
        "internalType": "string",
        "name": "str",
        "type": "string"
      }
    ],
    "name": "StringTooLong",
    "type": "error"
  },
  {
    "anonymous": false,
    "inputs": [],
    "name": "EIP712DomainChanged",
    "type": "event"
  },
  {
    "anonymous": false,
    "inputs": [
      {
        "indexed": false,
        "internalType": "address",
        "name": "creator",
        "type": "address"
      }
    ],
    "name": "GameCreated",
    "type": "event"
  },
  {
    "anonymous": false,
    "inputs": [
      {
        "indexed": false,
        "internalType": "address",
        "name": "winner",
        "type": "address"
      }
    ],
    "name": "GameEnded",
    "type": "event"
  },
  {
    "anonymous": false,
    "inputs": [],
    "name": "GameStarted",
    "type": "event"
  },
  {
    "anonymous": false,
    "inputs": [
      {
        "indexed": false,
        "internalType": "uint8",
        "name": "chainId",
        "type": "uint8"
      },
      {
        "indexed": false,
        "internalType": "uint8",
        "name": "x",
        "type": "uint8"
      },
      {
        "indexed": false,
        "internalType": "uint8",
        "name": "y",
        "type": "uint8"
      }
    ],
    "name": "HotelChainFormed",
    "type": "event"
  },
  {
    "anonymous": false,
    "inputs": [
      {
        "indexed": false,
        "internalType": "address",
        "name": "player",
        "type": "address"
      },
      {
        "indexed": false,
        "internalType": "uint256",
        "name": "playerId",
        "type": "uint256"
      }
    ],
    "name": "PlayerJoined",
    "type": "event"
  },
  {
    "anonymous": false,
    "inputs": [
      {
        "indexed": false,
        "internalType": "uint256",
        "name": "playerId",
        "type": "uint256"
      },
      {
        "indexed": false,
        "internalType": "uint8",
        "name": "chainId",
        "type": "uint8"
      },
      {
        "indexed": false,
        "internalType": "uint32",
        "name": "amount",
        "type": "uint32"
      }
    ],
    "name": "SharesPurchased",
    "type": "event"
  },
  {
    "anonymous": false,
    "inputs": [
      {
        "indexed": false,
        "internalType": "uint256",
        "name": "playerId",
        "type": "uint256"
      },
      {
        "indexed": false,
        "internalType": "uint8",
        "name": "x",
        "type": "uint8"
      },
      {
        "indexed": false,
        "internalType": "uint8",
        "name": "y",
        "type": "uint8"
      }
    ],
    "name": "TilePlaced",
    "type": "event"
  },
  {
    "inputs": [
      {
        "internalType": "uint256",
        "name": "",
        "type": "uint256"
      },
      {
        "internalType": "uint256",
        "name": "",
        "type": "uint256"
      }
    ],
    "name": "board",
    "outputs": [
      {
        "internalType": "euint8",
        "name": "hotelChain",
        "type": "uint256"
      },
      {
        "internalType": "ebool",
        "name": "isPlaced",
        "type": "uint256"
      }
    ],
    "stateMutability": "view",
    "type": "function"
  },
  {
    "inputs": [],
    "name": "eip712Domain",
    "outputs": [
      {
        "internalType": "bytes1",
        "name": "fields",
        "type": "bytes1"
      },
      {
        "internalType": "string",
        "name": "name",
        "type": "string"
      },
      {
        "internalType": "string",
        "name": "version",
        "type": "string"
      },
      {
        "internalType": "uint256",
        "name": "chainId",
        "type": "uint256"
      },
      {
        "internalType": "address",
        "name": "verifyingContract",
        "type": "address"
      },
      {
        "internalType": "bytes32",
        "name": "salt",
        "type": "bytes32"
      },
      {
        "internalType": "uint256[]",
        "name": "extensions",
        "type": "uint256[]"
      }
    ],
    "stateMutability": "view",
    "type": "function"
  },
  {
    "inputs": [],
    "name": "endGame",
    "outputs": [],
    "stateMutability": "nonpayable",
    "type": "function"
  },
  {
    "inputs": [],
    "name": "gameState",
    "outputs": [
      {
        "internalType": "uint8",
        "name": "playerCount",
        "type": "uint8"
      },
      {
        "internalType": "uint8",
        "name": "currentPlayerIndex",
        "type": "uint8"
      },
      {
        "internalType": "bool",
        "name": "gameStarted",
        "type": "bool"
      },
      {
        "internalType": "bool",
        "name": "gameEnded",
        "type": "bool"
      }
    ],
    "stateMutability": "view",
    "type": "function"
  },
  {
    "inputs": [],
    "name": "getCurrentPlayer",
    "outputs": [
      {
        "internalType": "address",
        "name": "",
        "type": "address"
      }
    ],
    "stateMutability": "view",
    "type": "function"
  },
  {
    "inputs": [
      {
        "internalType": "uint256",
        "name": "playerId",
        "type": "uint256"
      }
    ],
    "name": "getPlayerCash",
    "outputs": [
      {
        "internalType": "uint32",
        "name": "",
        "type": "uint32"
      }
    ],
    "stateMutability": "view",
    "type": "function"
  },
  {
    "inputs": [],
    "name": "getPlayerCount",
    "outputs": [
      {
        "internalType": "uint8",
        "name": "",
        "type": "uint8"
      }
    ],
    "stateMutability": "view",
    "type": "function"
  },
  {
    "inputs": [
      {
        "internalType": "uint256",
        "name": "playerId",
        "type": "uint256"
      },
      {
        "internalType": "uint8",
        "name": "chainId",
        "type": "uint8"
      },
      {
        "components": [
          {
            "internalType": "bytes32",
            "name": "publicKey",
            "type": "bytes32"
          },
          {
            "internalType": "bytes",
            "name": "signature",
            "type": "bytes"
          }
        ],
        "internalType": "struct Permission",
        "name": "permission",
        "type": "tuple"
      }
    ],
    "name": "getPlayerShares",
    "outputs": [
      {
        "internalType": "string",
        "name": "",
        "type": "string"
      }
    ],
    "stateMutability": "view",
    "type": "function"
  },
  {
    "inputs": [
      {
        "internalType": "uint256",
        "name": "playerId",
        "type": "uint256"
      },
      {
        "internalType": "uint8",
        "name": "tileIndex",
        "type": "uint8"
      },
      {
        "components": [
          {
            "internalType": "bytes32",
            "name": "publicKey",
            "type": "bytes32"
          },
          {
            "internalType": "bytes",
            "name": "signature",
            "type": "bytes"
          }
        ],
        "internalType": "struct Permission",
        "name": "permission",
        "type": "tuple"
      }
    ],
    "name": "getPlayerTile",
    "outputs": [
      {
        "internalType": "string",
        "name": "",
        "type": "string"
      }
    ],
    "stateMutability": "view",
    "type": "function"
  },
  {
    "inputs": [
      {
        "internalType": "uint8",
        "name": "",
        "type": "uint8"
      }
    ],
    "name": "hotelChainActive",
    "outputs": [
      {
        "internalType": "ebool",
        "name": "",
        "type": "uint256"
      }
    ],
    "stateMutability": "view",
    "type": "function"
  },
  {
    "inputs": [
      {
        "internalType": "uint8",
        "name": "",
        "type": "uint8"
      }
    ],
    "name": "hotelChainSizes",
    "outputs": [
      {
        "internalType": "euint32",
        "name": "",
        "type": "uint256"
      }
    ],
    "stateMutability": "view",
    "type": "function"
  },
  {
    "inputs": [],
    "name": "joinGame",
    "outputs": [
      {
        "internalType": "uint256",
        "name": "",
        "type": "uint256"
      }
    ],
    "stateMutability": "nonpayable",
    "type": "function"
  },
  {
    "inputs": [
      {
        "components": [
          {
            "internalType": "bytes",
            "name": "data",
            "type": "bytes"
          }
        ],
        "internalType": "struct inEuint8",
        "name": "encryptedTileIndex",
        "type": "tuple"
      },
      {
        "internalType": "uint8",
        "name": "x",
        "type": "uint8"
      },
      {
        "internalType": "uint8",
        "name": "y",
        "type": "uint8"
      },
      {
        "components": [
          {
            "internalType": "bytes32",
            "name": "publicKey",
            "type": "bytes32"
          },
          {
            "internalType": "bytes",
            "name": "signature",
            "type": "bytes"
          }
        ],
        "internalType": "struct Permission",
        "name": "permission",
        "type": "tuple"
      }
    ],
    "name": "placeTile",
    "outputs": [],
    "stateMutability": "nonpayable",
    "type": "function"
  },
  {
    "inputs": [
      {
        "internalType": "uint256",
        "name": "",
        "type": "uint256"
      }
    ],
    "name": "players",
    "outputs": [
      {
        "internalType": "address",
        "name": "playerAddress",
        "type": "address"
      },
      {
        "internalType": "uint32",
        "name": "cash",
        "type": "uint32"
      },
      {
        "internalType": "bool",
        "name": "isActive",
        "type": "bool"
      }
    ],
    "stateMutability": "view",
    "type": "function"
  },
  {
    "inputs": [
      {
        "components": [
          {
            "internalType": "bytes",
            "name": "data",
            "type": "bytes"
          }
        ],
        "internalType": "struct inEuint8",
        "name": "encryptedChainId",
        "type": "tuple"
      },
      {
        "components": [
          {
            "internalType": "bytes",
            "name": "data",
            "type": "bytes"
          }
        ],
        "internalType": "struct inEuint32",
        "name": "encryptedAmount",
        "type": "tuple"
      },
      {
        "components": [
          {
            "internalType": "bytes32",
            "name": "publicKey",
            "type": "bytes32"
          },
          {
            "internalType": "bytes",
            "name": "signature",
            "type": "bytes"
          }
        ],
        "internalType": "struct Permission",
        "name": "permission",
        "type": "tuple"
      }
    ],
    "name": "purchaseShares",
    "outputs": [],
    "stateMutability": "nonpayable",
    "type": "function"
  },
  {
    "inputs": [],
    "name": "startGame",
    "outputs": [],
    "stateMutability": "nonpayable",
    "type": "function"
  }
]